LICENSE
MANIFEST.in
README.md
pyproject.toml
requirements.txt
setup.cfg
setup.py
docs/Makefile
docs/conda_requirements.txt
docs/conf.py
docs/index.rst
docs/make.bat
docs/markdown.md
docs/requirements.txt
docs/notebooks/00_tutorial.ipynb
docs/notebooks/01_sampling_data.ipynb
docs/notebooks/02_database_reference.ipynb
docs/notebooks/03_coaxial_waveguide.ipynb
src/pymwm/__init__.py
src/pymwm/cutoff.py
src/pymwm/py.typed
src/pymwm/waveguide.py
src/pymwm.egg-info/PKG-INFO
src/pymwm.egg-info/SOURCES.txt
src/pymwm.egg-info/dependency_links.txt
src/pymwm.egg-info/entry_points.txt
src/pymwm.egg-info/not-zip-safe
src/pymwm.egg-info/requires.txt
src/pymwm.egg-info/top_level.txt
src/pymwm/bin/__init__.py
src/pymwm/bin/split_pymwm_h5.py
src/pymwm/bin/update_pymwm_h5.py
src/pymwm/coax/__init__.py
src/pymwm/coax/samples/__init__.py
src/pymwm/cylinder/__init__.py
src/pymwm/cylinder/samples/__init__.py
src/pymwm/slit/__init__.py
src/pymwm/slit/samples/__init__.py
src/pymwm/utils/__init__.pxd
src/pymwm/utils/__init__.py
src/pymwm/utils/bessel_utils.pxd
src/pymwm/utils/bessel_utils.pyx
src/pymwm/utils/coax_utils.pxd
src/pymwm/utils/coax_utils.pyi
src/pymwm/utils/coax_utils.pyx
src/pymwm/utils/cutoff_utils.pxd
src/pymwm/utils/cutoff_utils.pyi
src/pymwm/utils/cutoff_utils.pyx
src/pymwm/utils/cylinder_utils.pxd
src/pymwm/utils/cylinder_utils.pyi
src/pymwm/utils/cylinder_utils.pyx
src/pymwm/utils/eig_mat_utils.pxd
src/pymwm/utils/eig_mat_utils.pyi
src/pymwm/utils/eig_mat_utils.pyx
src/pymwm/utils/py.typed
src/pymwm/utils/slit_utils.pxd
src/pymwm/utils/slit_utils.pyi
src/pymwm/utils/slit_utils.pyx
tests/test_bessel_integral.py
tests/test_bessel_utils.py
tests/test_coax.py
tests/test_coax_coef.py
tests/test_coax_eig_mat.py
tests/test_coax_samples.py
tests/test_coax_utils.py
tests/test_cutoff.py
tests/test_cylinder.py
tests/test_cylinder_coefs.py
tests/test_cylinder_eig_mat.py
tests/test_cylinder_samples.py
tests/test_cylinder_utils.py
tests/test_database.py
tests/test_eig_mat_utils.py
tests/test_slit.py
tests/test_slit_coefs.py
tests/test_slit_samples.py