Metadata-Version: 2.1
Name: pymwm
Version: 0.5.6
Summary: A metallic waveguide mode solver
Home-page: https://github.com/mnishida/PyMWM
Author: Munehiro Nishida
Author-email: mnishida@hiroshima-u.ac.jp
License: MIT
Keywords: metallic waveguide mode,electromagnetism
Classifier: Development Status :: 4 - Beta
Classifier: License :: OSI Approved :: MIT License
Classifier: Programming Language :: Python
Classifier: Programming Language :: Python :: 3
Classifier: Topic :: Scientific/Engineering
Requires-Python: >=3.7
License-File: LICENSE
Requires-Dist: Cython
Requires-Dist: numpy
Requires-Dist: scipy
Requires-Dist: pandas
Requires-Dist: ray
Requires-Dist: matplotlib
Requires-Dist: riip
